{
"type": "FeatureCollection",
"name": "kindergarten",
"crs": { "type": "name", "properties": { "name": "urn:ogc:def:crs:OGC:1.3:CRS84" } },
"features": [
{ "type": "Feature", "properties": { "capacity": 250 }, "geometry": { "type": "Point", "coordinates": [ 30.330162, 59.988234 ] } },
{ "type": "Feature", "properties": { "capacity": 250 }, "geometry": { "type": "Point", "coordinates": [ 30.332038, 59.987674 ] } },
{ "type": "Feature", "properties": { "capacity": 250 }, "geometry": { "type": "Point", "coordinates": [ 30.381262055612225, 59.986639963878524 ] } },
{ "type": "Feature", "properties": { "capacity": 250 }, "geometry": { "type": "Point", "coordinates": [ 30.383868041045528, 59.985291152061116 ] } },
{ "type": "Feature", "properties": { "capacity": 250 }, "geometry": { "type": "Point", "coordinates": [ 30.350359, 59.997007 ] } },
{ "type": "Feature", "properties": { "capacity": 250 }, "geometry": { "type": "Point", "coordinates": [ 30.353445, 59.996285 ] } },
{ "type": "Feature", "properties": { "capacity": 250 }, "geometry": { "type": "Point", "coordinates": [ 30.341912745483206, 59.971548290325352 ] } },
{ "type": "Feature", "properties": { "capacity": 250 }, "geometry": { "type": "Point", "coordinates": [ 30.333314, 59.98555 ] } },
{ "type": "Feature", "properties": { "capacity": 250 }, "geometry": { "type": "Point", "coordinates": [ 30.3475813, 59.9850494 ] } },
{ "type": "Feature", "properties": { "capacity": 250 }, "geometry": { "type": "Point", "coordinates": [ 30.373019182840494, 59.987042702848107 ] } },
{ "type": "Feature", "properties": { "capacity": 250 }, "geometry": { "type": "Point", "coordinates": [ 30.343009484157729, 59.984311401941099 ] } },
{ "type": "Feature", "properties": { "capacity": 250 }, "geometry": { "type": "Point", "coordinates": [ 30.343849, 59.996948 ] } },
{ "type": "Feature", "properties": { "capacity": 250 }, "geometry": { "type": "Point", "coordinates": [ 30.351317995859507, 59.9835998418109 ] } },
{ "type": "Feature", "properties": { "capacity": 250 }, "geometry": { "type": "Point", "coordinates": [ 30.349416706869395, 59.982330576233018 ] } },
{ "type": "Feature", "properties": { "capacity": 250 }, "geometry": { "type": "Point", "coordinates": [ 30.335915350684747, 59.977303418057787 ] } },
{ "type": "Feature", "properties": { "capacity": 250 }, "geometry": { "type": "Point", "coordinates": [ 30.331900681645973, 59.979378433422703 ] } },
{ "type": "Feature", "properties": { "capacity": 250 }, "geometry": { "type": "Point", "coordinates": [ 30.350736336411522, 59.979499837760713 ] } },
{ "type": "Feature", "properties": { "capacity": 250 }, "geometry": { "type": "Point", "coordinates": [ 30.37058211319302, 59.980637020914493 ] } },
{ "type": "Feature", "properties": { "capacity": 250 }, "geometry": { "type": "Point", "coordinates": [ 30.369663418544885, 59.979996173216833 ] } },
{ "type": "Feature", "properties": { "capacity": 250 }, "geometry": { "type": "Point", "coordinates": [ 30.37381561089996, 59.976920644175699 ] } },
{ "type": "Feature", "properties": { "capacity": 250 }, "geometry": { "type": "Point", "coordinates": [ 30.392651908205085, 59.98257076075739 ] } },
{ "type": "Feature", "properties": { "capacity": 250 }, "geometry": { "type": "Point", "coordinates": [ 30.386633974797657, 59.973955244686053 ] } },
{ "type": "Feature", "properties": { "capacity": 350 }, "geometry": { "type": "Point", "coordinates": [ 30.364208073820194, 59.98874410820288 ] } },
{ "type": "Feature", "properties": { "capacity": 250 }, "geometry": { "type": "Point", "coordinates": [ 30.344740790582804, 59.99969773170605 ] } },
{ "type": "Feature", "properties": { "capacity": 250 }, "geometry": { "type": "Point", "coordinates": [ 30.356721565697416, 60.001196009439035 ] } },
{ "type": "Feature", "properties": { "capacity": 250 }, "geometry": { "type": "Point", "coordinates": [ 30.356736965104442, 59.982956931878007 ] } },
{ "type": "Feature", "properties": { "capacity": 250 }, "geometry": { "type": "Point", "coordinates": [ 30.358502417001798, 59.983125997804137 ] } }
]
}
